eve_glue/__init__.py
eve_glue/bitmask.py
eve_glue/calendar.py
eve_glue/containers.py
eve_glue/corp_roles.py
eve_glue/enums.py
eve_glue/faction_warfare.py
eve_glue/industry_job_status.py
eve_glue/location_flag.py
eve_glue/location_type.py
eve_glue/notification_type.py
eve_glue/order_range.py
eve_glue/order_state.py
eve_glue/poco.py
eve_glue/starbase.py
eve_glue/wallet_journal_ref.py
eve_glue-0.0.9.dist-info/METADATA
eve_glue-0.0.9.dist-info/RECORD
eve_glue-0.0.9.dist-info/WHEEL
eve_glue-0.0.9.dist-info/top_level.txt
