Metadata-Version: 2.1
Name: eve-glue
Version: 0.0.9
Summary: eve-glue
Home-page: https://github.com/ccpgames/eve-glue
Author: Team Tech Co
Author-email: teamtechco@ccpgames.com
License: UNKNOWN
Platform: UNKNOWN
Classifier: Development Status :: 3 - Alpha
Classifier: Environment :: Web Environment
Classifier: Framework :: Flask
Classifier: Operating System :: POSIX :: Linux
Classifier: Programming Language :: Python :: 3.5
Classifier: License :: OSI Approved :: MIT License
